__init__.py
pySqlServer.py
pySqlServer_old.py
pySqlServer-3.7.0.dist-info/LICENSE
pySqlServer-3.7.0.dist-info/METADATA
pySqlServer-3.7.0.dist-info/WHEEL
pySqlServer-3.7.0.dist-info/top_level.txt
pySqlServer-3.7.0.dist-info/RECORD
