Metadata-Version: 2.1
Name: pySqlServer
Version: 3.7.0
Summary: PySQL is a Python library for interacting with SQL Server databases. It provides a simplified methodes for common database operations.
Author-email: Sajad Khanbabaie <khanbabaie.sa@gmail.com>
Project-URL: Homepage, https://github.com/sajad-git/PySQL
Classifier: Programming Language :: Python :: 3
Classifier: License :: OSI Approved :: MIT License
Classifier: Operating System :: OS Independent
Requires-Python: >=3.9
License-File: LICENSE
